marketa/__init__.py
marketa/cli.py
marketa/data/__init__.py
marketa/data/application.py
marketa/data/base.py
marketa/data/instrument.py
marketa/data/instrument_data.py
marketa/data/market.py
marketa/data/price_daily.py
marketa/data/price_intraday.py
marketa/data/repository.py
marketa/data/repository_base.py
marketa/data/security_type.py
marketa/data/watchlist.py
marketa/entities/__init__.py
marketa/entities/ticker.py
marketa/facade.py
marketa/install.py
marketa/services/__init__.py
marketa/services/feed.py
marketa/shared/__init__.py
marketa/shared/constants.py
marketa/shared/container.py
marketa/shared/exceptions.py
marketa/shared/extensions.py
marketa/shared/taskeeper.py
marketa/shared/utils.py
marketa/template.service
marketa-0.1.9.dist-info/entry_points.txt
marketa-0.1.9.dist-info/WHEEL
marketa-0.1.9.dist-info/METADATA
marketa-0.1.9.dist-info/RECORD
